MIPS_Datapath.v
module MIPS_Datapath (
    input [31:0] instruction,   // 32-bit instruction input
    input clk,                  // Clock signal
    input reset,                // Reset signal
    input regWrite, memWrite, memRead, // Control signals
    input branch,               // Branch control signal
    input [2:0] aluControl,     // ALU control signal
    output [31:0] aluResult,    // ALU result
    output [31:0] memDataOut,   // Memory read output
    output zero,                // Zero flag
    output [31:0] pc            // Program Counter
);

    // Internal signals
    reg [31:0] pc_reg; // Program Counter register
    wire [31:0] pc_next, pc_plus4, branch_target;
    wire [31:0] regData1, regData2, signExtImm, aluInput2;
    wire [31:0] branchOffset;
    wire branchTaken;

    // Initialize PC
    always @(posedge clk or posedge reset) begin
        if (reset)
            pc_reg <= 32'b0;
        else
            pc_reg <= pc_next;
    end

    assign pc = pc_reg;

    // PC + 4
    assign pc_plus4 = pc_reg + 4;

    // Sign extension for immediate value
    SignExtender signExtender (
        .in(instruction[15:0]),
        .out(signExtImm)
    );

    // Branch target calculation
    assign branchOffset = signExtImm << 2;
    assign branch_target = pc_plus4 + branchOffset;

    // Branch condition
    assign branchTaken = branch & zero;
    assign pc_next = branchTaken ? branch_target : pc_plus4;

    // Register File
    RegisterFile registerFile (
        .clk(clk),
        .regWrite(regWrite),
        .readReg1(instruction[25:21]),
        .readReg2(instruction[20:16]),
        .writeReg(instruction[15:11]),
        .writeData(aluResult),
        .readData1(regData1),
        .readData2(regData2)
    );

    // ALU input multiplexer
    Mux2to1 aluMux (
        .in0(regData2),
        .in1(signExtImm),
        .sel(instruction[28]), // Immediate selection
        .out(aluInput2)
    );

    // ALU
    ALU alu (
        .in1(regData1),
        .in2(aluInput2),
        .aluControl(aluControl),
        .result(aluResult),
        .zero(zero)
    );

    // Data Memory
    DataMemory dataMemory (
        .clk(clk),
        .memWrite(memWrite),
        .memRead(memRead),
        .address(aluResult),
        .writeData(regData2),
        .readData(memDataOut)
    );

endmodule

// Sign Extender Module
module SignExtender (
    input [15:0] in,
    output [31:0] out
);
    assign out = {{16{in[15]}}, in};
endmodule

// Register File Module
module RegisterFile (
    input clk,
    input regWrite,
    input [4:0] readReg1,
    input [4:0] readReg2,
    input [4:0] writeReg,
    input [31:0] writeData,
    output [31:0] readData1,
    output [31:0] readData2
);
    reg [31:0] registers [0:31];
    assign readData1 = registers[readReg1];
    assign readData2 = registers[readReg2];
    always @(posedge clk) begin
        if (regWrite)
            registers[writeReg] <= writeData;
    end
endmodule

// 2-to-1 Multiplexer Module
module Mux2to1 (
    input [31:0] in0,
    input [31:0] in1,
    input sel,
    output [31:0] out
);
    assign out = (sel) ? in1 : in0;
endmodule

// ALU Module
module ALU (
    input [31:0] in1,
    input [31:0] in2,
    input [2:0] aluControl,
    output reg [31:0] result,
    output zero
);
    always @(*) begin
        case (aluControl)
            3'b010: result = in1 + in2; // ADD
            3'b110: result = in1 - in2; // SUB
            3'b000: result = in1 & in2; // AND
            3'b001: result = in1 | in2; // OR
            default: result = 32'b0;
        endcase
    end
    assign zero = (result == 32'b0);
endmodule

// Data Memory Module
module DataMemory (
    input clk,
    input memWrite,
    input memRead,
    input [31:0] address,
    input [31:0] writeData,
    output [31:0] readData
);
    reg [31:0] memory [0:255];
    assign readData = (memRead) ? memory[address[7:0]] : 32'b0;
    always @(posedge clk) begin
        if (memWrite)
            memory[address[7:0]] <= writeData;
    end
endmodule

MIPS_Datapath_tb.v
`include "MIPS_Datapath.v"
module MIPS_Datapath_tb;
    // Inputs
    reg clk;
    reg reset;
    reg regWrite;
    reg memWrite;
    reg memRead;
    reg branch;
    reg [2:0] aluControl;
    reg [31:0] instruction;

    // Outputs
    wire [31:0] aluResult;
    wire [31:0] memDataOut;
    wire zero;
    wire [31:0] pc;

    // Memory for simulation
    reg [31:0] memory [0:31]; // 32 words of memory

    // Instantiate the Unit Under Test (UUT)
    MIPS_Datapath uut (
        .instruction(instruction),
        .clk(clk),
        .reset(reset),
        .regWrite(regWrite),
        .memWrite(memWrite),
        .memRead(memRead),
        .branch(branch),
        .aluControl(aluControl),
        .aluResult(aluResult),
        .memDataOut(memDataOut),
        .zero(zero),
        .pc(pc)
    );

    // Clock generation
    initial begin
        clk = 0;
        forever #5 clk = ~clk;
    end

    initial begin
        $dumpfile("waveform.vcd"); 
        $dumpvars(0, MIPS_Datapath_tb); 
    end
    
    // Test cases
    initial begin
        // Initialize inputs
        reset = 1;
        regWrite = 0;
        memWrite = 0;
        memRead = 0;
        branch = 0;
        aluControl = 3'b000;
        instruction = 32'b0;

        // Initialize memory
        memory[1] = 1;
        memory[2] = 2;
        memory[4] = 4;
        memory[5] = 5;
        #10;

        reset = 0;

        // Test R-type instruction (ADD: opcode = 0, funct = 32)
        instruction = 32'b000000_00001_00010_00011_00000_100000; // ADD $3, $1, $2
        regWrite = 1;
        aluControl = 3'b010; // ADD operation
        #10;

        // Validate output for ADD
        if (aluResult !== (memory[1] + memory[2])) $display("ADD test failed");

        // Test R-type instruction (SUB: opcode = 0, funct = 34)
        instruction = 32'b000000_00100_00101_00110_00000_100010; // SUB $6, $4, $5
        regWrite = 1;
        aluControl = 3'b110; // SUB operation
        #10;

        // Validate output for SUB
        if (aluResult !== (memory[4] - memory[5])) $display("SUB test failed");

        // Test R-type instruction (AND: opcode = 0, funct = 36)
        instruction = 32'b000000_00011_00001_00111_00000_100100; // AND $7, $3, $1
        regWrite = 1;
        aluControl = 3'b000; // AND operation
        #10;

        // Validate output for AND
        if (aluResult !== (memory[3] & memory[1])) $display("AND test failed");

        // Test R-type instruction (OR: opcode = 0, funct = 37)
        instruction = 32'b000000_00101_00100_01000_00000_100101; // OR $8, $5, $4
        regWrite = 1;
        aluControl = 3'b001; // OR operation
        #10;

        // Validate output for OR
        if (aluResult !== (memory[5] | memory[4])) $display("OR test failed");

        // Test I-type instruction (LW: opcode = 35)
        instruction = 32'b100011_00001_00100_0000_0000_0000_0100; // LW $4, 4($1)
        memRead = 1;
        regWrite = 1;
        aluControl = 3'b010; // ADD for address calculation
        #10;

        // Validate output for LW
        if (memDataOut !== memory[memory[1] + 4]) $display("LW test failed");

        // Test I-type instruction (SW: opcode = 43)
        instruction = 32'b101011_00001_00101_0000_0000_0000_1000; // SW $5, 8($1)
        memWrite = 1;
        regWrite = 0;
        aluControl = 3'b010; // ADD for address calculation
        #10;

        // Validate output for SW (Check memory content)
        if (memory[memory[1] + 8] !== memory[5]) $display("SW test failed");

        // Test J-type instruction (J: opcode = 2)
        instruction = 32'b000010_00000_00000_00000_00000_001010; // J 10
        branch = 1;
        aluControl = 3'b010; // PC update
        #10;

        // Validate PC for J
        if (pc !== 10) $display("J test failed");

        // Test J-type instruction (J: opcode = 2, different target)
        instruction = 32'b000010_00000_00000_00000_00000_001100; // J 12
        branch = 1;
        aluControl = 3'b010; // PC update
        #10;

        // Validate PC for J
        if (pc !== 12) $display("J (different target) test failed");

        // Finish simulation
        $stop;
    end
endmodule

waveform.vcd
$date
	Fri Dec 20 20:02:01 2024
$end
$version
	Icarus Verilog
$end
$timescale
	1s
$end
$scope module MIPS_Datapath_tb $end
$var wire 1 ! zero $end
$var wire 32 " pc [31:0] $end
$var wire 32 # memDataOut [31:0] $end
$var wire 32 $ aluResult [31:0] $end
$var reg 3 % aluControl [2:0] $end
$var reg 1 & branch $end
$var reg 1 ' clk $end
$var reg 32 ( instruction [31:0] $end
$var reg 1 ) memRead $end
$var reg 1 * memWrite $end
$var reg 1 + regWrite $end
$var reg 1 , reset $end
$scope module uut $end
$var wire 3 - aluControl [2:0] $end
$var wire 1 & branch $end
$var wire 1 . branchTaken $end
$var wire 1 ' clk $end
$var wire 32 / instruction [31:0] $end
$var wire 1 ) memRead $end
$var wire 1 * memWrite $end
$var wire 32 0 pc [31:0] $end
$var wire 1 + regWrite $end
$var wire 1 , reset $end
$var wire 1 ! zero $end
$var wire 32 1 signExtImm [31:0] $end
$var wire 32 2 regData2 [31:0] $end
$var wire 32 3 regData1 [31:0] $end
$var wire 32 4 pc_plus4 [31:0] $end
$var wire 32 5 pc_next [31:0] $end
$var wire 32 6 memDataOut [31:0] $end
$var wire 32 7 branch_target [31:0] $end
$var wire 32 8 branchOffset [31:0] $end
$var wire 32 9 aluResult [31:0] $end
$var wire 32 : aluInput2 [31:0] $end
$var reg 32 ; pc_reg [31:0] $end
$scope module alu $end
$var wire 3 < aluControl [2:0] $end
$var wire 1 ! zero $end
$var wire 32 = in2 [31:0] $end
$var wire 32 > in1 [31:0] $end
$var reg 32 ? result [31:0] $end
$upscope $end
$scope module aluMux $end
$var wire 1 @ sel $end
$var wire 32 A out [31:0] $end
$var wire 32 B in1 [31:0] $end
$var wire 32 C in0 [31:0] $end
$upscope $end
$scope module dataMemory $end
$var wire 32 D address [31:0] $end
$var wire 1 ' clk $end
$var wire 1 ) memRead $end
$var wire 1 * memWrite $end
$var wire 32 E writeData [31:0] $end
$var wire 32 F readData [31:0] $end
$upscope $end
$scope module registerFile $end
$var wire 1 ' clk $end
$var wire 32 G readData1 [31:0] $end
$var wire 32 H readData2 [31:0] $end
$var wire 5 I readReg1 [4:0] $end
$var wire 5 J readReg2 [4:0] $end
$var wire 1 + regWrite $end
$var wire 32 K writeData [31:0] $end
$var wire 5 L writeReg [4:0] $end
$upscope $end
$scope module signExtender $end
$var wire 16 M in [15:0] $end
$var wire 32 N out [31:0] $end
$upscope $end
$upscope $end
$upscope $end
$enddefinitions $end
$comment Show the parameter values. $end
$dumpall
$end
#0
$dumpvars
b0 N
b0 M
b0 L
bx K
b0 J
b0 I
bx H
bx G
b0 F
bx E
bx D
bx C
b0 B
bx A
0@
bx ?
bx >
bx =
b0 <
b0 ;
bx :
bx 9
b0 8
b100 7
b0 6
b100 5
b100 4
bx 3
bx 2
b0 1
b0 0
b0 /
0.
b0 -
1,
0+
0*
0)
b0 (
0'
0&
b0 %
bx $
b0 #
b0 "
x!
$end
#5
1'
#10
b110000010000100 7
b110000010000000 8
b1100000100000 1
b1100000100000 B
b1100000100000 N
b1100000100000 M
b1 I
b10 J
b11 L
0'
b10 %
b10 -
b10 <
1+
b1000100001100000100000 (
b1000100001100000100000 /
0,
#15
b1000 5
b110000010001000 7
b1000 4
b100 "
b100 0
b100 ;
1'
#20
b1100000010010000 7
b1100000010001000 8
b11000000100010 1
b11000000100010 B
b11000000100010 N
b11000000100010 M
b100 I
b101 J
b110 L
0'
b110 %
b110 -
b110 <
b100001010011000000100010 (
b100001010011000000100010 /
#25
b1100 5
b1100000010010100 7
b1100 4
b1000 "
b1000 0
b1000 ;
1'
#30
b1110000010011100 7
b1110000010010000 8
b11100000100100 1
b11100000100100 B
b11100000100100 N
b11100000100100 M
b11 I
b1 J
b111 L
0'
b0 %
b0 -
b0 <
b11000010011100000100100 (
b11000010011100000100100 /
#35
b10000 5
b1110000010100000 7
b10000 4
b1100 "
b1100 0
b1100 ;
1'
#40
b10000000010100100 7
b10000000010010100 8
b100000000100101 1
b100000000100101 B
b100000000100101 N
b100000000100101 M
b101 I
b100 J
b1000 L
0'
b1 %
b1 -
b1 <
b101001000100000000100101 (
b101001000100000000100101 /
#45
b10100 5
b10000000010101000 7
b10100 4
b10000 "
b10000 0
b10000 ;
1'
#50
b100100 7
b10000 8
bx #
bx 6
bx F
b100 1
b100 B
b100 N
b100 M
b1 I
b0 L
0'
b10 %
b10 -
b10 <
1)
b10001100001001000000000000000100 (
b10001100001001000000000000000100 /
#55
b11000 5
b101000 7
b11000 4
b10100 "
b10100 0
b10100 ;
1'
#60
b111000 7
b100000 8
b1000 1
b1000 B
b1000 N
b1000 M
b101 J
0'
0+
1*
b10101100001001010000000000001000 (
b10101100001001010000000000001000 /
#65
b11100 5
b111100 7
b11100 4
b11000 "
b11000 0
b11000 ;
1'
#70
b0x0xx100 5
b1000100 7
b101000 8
x.
b1010 1
b1010 B
b1010 N
b1010 M
b0 I
b0 J
0'
1&
b1000000000000000000000001010 (
b1000000000000000000000001010 /
#75
bx 5
bx 7
bx 4
b0x0xx100 "
b0x0xx100 0
b0x0xx100 ;
1'
#80
b110000 8
b1100 1
b1100 B
b1100 N
b1100 M
0'
b1000000000000000000000001100 (
b1000000000000000000000001100 /
#85
bx "
bx 0
bx ;
1'
